causality/__init__.py
causality/util.py
causality/analysis/__init__.py
causality/analysis/dataframe.py
causality/estimation/__init__.py
causality/estimation/adjustments.py
causality/estimation/nonparametric.py
causality/estimation/parametric.py
causality/inference/__init__.py
causality/inference/independence_tests/__init__.py
causality/inference/search/__init__.py
causality-0.0.11.dist-info/LICENSE.txt
causality-0.0.11.dist-info/METADATA
causality-0.0.11.dist-info/WHEEL
causality-0.0.11.dist-info/top_level.txt
causality-0.0.11.dist-info/RECORD
