Metadata-Version: 2.2
Name: causality
Version: 0.0.11
Summary: Tools for causal inference
Home-page: http://github.com/akelleh/causality
Author: Adam Kelleher
Author-email: akelleh@gmail.com
License: MIT
Keywords: causality data analysis inference causal graphs DAG propensity score matching
Classifier: Development Status :: 3 - Alpha
Classifier: Intended Audience :: Developers
Classifier: Intended Audience :: Science/Research
Classifier: Intended Audience :: Education
Classifier: Topic :: Scientific/Engineering :: Mathematics
Classifier: Topic :: Scientific/Engineering :: Information Analysis
Classifier: Topic :: Scientific/Engineering :: Bio-Informatics
Classifier: Topic :: Scientific/Engineering :: Artificial Intelligence
Classifier: Topic :: Scientific/Engineering
Classifier: License :: OSI Approved :: MIT License
Classifier: Programming Language :: Python :: 2.7
License-File: LICENSE.txt
Requires-Dist: numpy
Requires-Dist: scipy
Requires-Dist: pandas
Requires-Dist: statsmodels
Requires-Dist: networkx
Requires-Dist: patsy
Requires-Dist: pytz
Requires-Dist: python-dateutil
Requires-Dist: decorator
Requires-Dist: pytz
Requires-Dist: six
Dynamic: author
Dynamic: author-email
Dynamic: classifier
Dynamic: description
Dynamic: description-content-type
Dynamic: home-page
Dynamic: keywords
Dynamic: license
Dynamic: requires-dist
Dynamic: summary
